hex_maze_neuro-1.0.4.dist-info/licenses/LICENSE
hexmaze/__init__.py
hexmaze/barrier_shift.py
hexmaze/core.py
hexmaze/plotting.py
hexmaze/utils.py
hex_maze_neuro-1.0.4.dist-info/METADATA
hex_maze_neuro-1.0.4.dist-info/WHEEL
hex_maze_neuro-1.0.4.dist-info/top_level.txt
hex_maze_neuro-1.0.4.dist-info/RECORD
