Metadata-Version: 2.4
Name: hex-maze-neuro
Version: 1.0.4
Summary: A Python toolkit for generating, visualizing, and analyzing hex maze configurations and optimal barrier change sequences for the hex maze task developed by the Berke Lab at UCSF.
Author-email: Stephanie Crater <stephcrater@berkeley.edu>
License-Expression: MIT
Project-URL: Homepage, https://github.com/calderast/Hex-maze
Project-URL: Bug Tracker, https://github.com/calderast/Hex-maze/issues
Classifier: Programming Language :: Python :: 3
Classifier: Operating System :: OS Independent
Classifier: Intended Audience :: Science/Research
Requires-Python: >=3.9
License-File: LICENSE
Requires-Dist: networkx>=3.3
Requires-Dist: matplotlib
Requires-Dist: numpy>=2.0.0
Requires-Dist: pandas
Requires-Dist: tqdm
Dynamic: license-file
